appconfigs/__init__.py
appconfigs/base.py
appconfigs/user.py
appconfigs-0.2.0.dist-info/LICENSE
appconfigs-0.2.0.dist-info/METADATA
appconfigs-0.2.0.dist-info/WHEEL
appconfigs-0.2.0.dist-info/top_level.txt
appconfigs-0.2.0.dist-info/RECORD
